calcgp/__init__.py
calcgp/containers.py
calcgp/distributions.py
calcgp/gps.py
calcgp/likelihood.py
calcgp/mean_functions.py
calcgp/optimize.py
calcgp/typing.py
calcgp/utils.py
calcgp/_deprecated/__init__.py
calcgp/_deprecated/base_covar.py
calcgp/_deprecated/covar.py
calcgp/_deprecated/distributions.py
calcgp/_deprecated/full_regression.py
calcgp/_deprecated/kernels.py
calcgp/_deprecated/likelihood.py
calcgp/_deprecated/logger.py
calcgp/_deprecated/optimizer.py
calcgp/_deprecated/posterior.py
calcgp/_deprecated/serialize.py
calcgp/_deprecated/sparse_regression.py
calcgp/_deprecated/utils.py
calcgp/gpjax_base/__init__.py
calcgp/gpjax_base/module.py
calcgp/gpjax_base/param.py
calcgp/kernels/__init__.py
calcgp/kernels/base.py
calcgp/kernels/compute_covariance.py
calcgp/kernels/non_stationary/__init__.py
calcgp/kernels/non_stationary/linear.py
calcgp/kernels/stationary/__init__.py
calcgp/kernels/stationary/periodic.py
calcgp/kernels/stationary/rbf.py
calcgp/td_integration/__init__.py
calcgp/td_integration/data_functions.py
calcgp/td_integration/gibbs_model.py
calcgp/td_integration/utils.py
calcgp-0.1.15.dist-info/LICENSE
calcgp-0.1.15.dist-info/METADATA
calcgp-0.1.15.dist-info/WHEEL
calcgp-0.1.15.dist-info/top_level.txt
calcgp-0.1.15.dist-info/RECORD
