Metadata-Version: 2.1
Name: calcgp
Version: 0.1.15
Summary: Gaussian Process Regression framework for numerical integration and differentiation
Home-page: https://github.com/LukasEin/calcgp.git
Author: Lukas Einramhof
Author-email: lukas.einramhof@gmail.com
License: MIT License
Classifier: Intended Audience :: Science/Research
Classifier: Programming Language :: Python :: 3
Classifier: Programming Language :: Python :: 3.8
Classifier: Programming Language :: Python :: 3.9
Classifier: Programming Language :: Python :: 3.10
License-File: LICENSE
Requires-Dist: jaxlib
Requires-Dist: jax
Requires-Dist: jaxtyping
Requires-Dist: jaxopt
Requires-Dist: simple-pytree (==0.1.7)
Requires-Dist: tensorflow-probability
Requires-Dist: orbax-checkpoint
Provides-Extra: testing
Requires-Dist: pytest (>=5.0) ; extra == 'testing'
